loci_client/__init__.py
loci_client/api/__init__.py
loci_client/api/default_api.py
loci_client/api_client.py
loci_client/api_response.py
loci_client/configuration.py
loci_client/exceptions.py
loci_client/models/__init__.py
loci_client/models/api_key_in.py
loci_client/models/api_key_out.py
loci_client/models/api_key_sort_enum.py
loci_client/models/api_keys_out.py
loci_client/models/artifact_export.py
loci_client/models/artifact_file_location_out.py
loci_client/models/artifact_in.py
loci_client/models/artifact_note.py
loci_client/models/artifact_note_export.py
loci_client/models/artifact_note_in.py
loci_client/models/artifact_note_type_enum.py
loci_client/models/artifact_note_update_in.py
loci_client/models/artifact_out.py
loci_client/models/artifact_priority_enum.py
loci_client/models/artifact_sort_enum.py
loci_client/models/artifact_type_enum.py
loci_client/models/artifacts_out.py
loci_client/models/http_validation_error.py
loci_client/models/message.py
loci_client/models/new_password.py
loci_client/models/order_by_enum.py
loci_client/models/project_access_user.py
loci_client/models/project_export.py
loci_client/models/project_in.py
loci_client/models/project_out.py
loci_client/models/project_sort_enum.py
loci_client/models/projects_out.py
loci_client/models/status_out.py
loci_client/models/token.py
loci_client/models/update_password.py
loci_client/models/user_create.py
loci_client/models/user_create_open.py
loci_client/models/user_full_out.py
loci_client/models/user_out.py
loci_client/models/user_update.py
loci_client/models/user_update_me.py
loci_client/models/users_out.py
loci_client/models/validation_error.py
loci_client/models/validation_error_loc_inner.py
loci_client/py.typed
loci_client/rest.py
loci_client-0.20250109.4844.dist-info/METADATA
loci_client-0.20250109.4844.dist-info/WHEEL
loci_client-0.20250109.4844.dist-info/RECORD
