Metadata-Version: 2.3
Name: loci_client
Version: 0.20250109.4844
Summary: Loci Notes Server
Home-page: https://github.com/GIT_USER_ID/GIT_REPO_ID
License: GNU General Public License v3.0
Keywords: OpenAPI,OpenAPI-Generator,Loci Notes Server
Author: TheTwitchy
Author-email: thetwitchy@thetwitchy.com
Requires-Python: >=3.8,<4.0
Classifier: License :: Other/Proprietary License
Classifier: Programming Language :: Python :: 3
Classifier: Programming Language :: Python :: 3.8
Classifier: Programming Language :: Python :: 3.9
Classifier: Programming Language :: Python :: 3.10
Classifier: Programming Language :: Python :: 3.11
Classifier: Programming Language :: Python :: 3.12
Classifier: Programming Language :: Python :: 3.13
Requires-Dist: pydantic (>=2)
Requires-Dist: python-dateutil (>=2.8.2)
Requires-Dist: typing-extensions (>=4.7.1)
Requires-Dist: urllib3 (>=1.25.3,<3.0.0)
Project-URL: Repository, https://github.com/GIT_USER_ID/GIT_REPO_ID
